setup.py
Products/__init__.py
Products.AdvancedQuery.egg-info/PKG-INFO
Products.AdvancedQuery.egg-info/SOURCES.txt
Products.AdvancedQuery.egg-info/dependency_links.txt
Products.AdvancedQuery.egg-info/namespace_packages.txt
Products.AdvancedQuery.egg-info/not-zip-safe
Products.AdvancedQuery.egg-info/requires.txt
Products.AdvancedQuery.egg-info/top_level.txt
Products/AdvancedQuery/AdvancedQuery.py
Products/AdvancedQuery/LICENSE.txt
Products/AdvancedQuery/README.txt
Products/AdvancedQuery/VERSION.txt
Products/AdvancedQuery/__init__.py
Products/AdvancedQuery/configure.zcml
Products/AdvancedQuery/ranking.py
Products/AdvancedQuery/sorting.py
Products/AdvancedQuery/tree.py
Products/AdvancedQuery/doc/AdvancedQuery.html
Products/AdvancedQuery/doc/style.css
Products/AdvancedQuery/eval/__init__.py
Products/AdvancedQuery/eval/context.py
Products/AdvancedQuery/eval/interfaces.py
Products/AdvancedQuery/eval/lib.py
Products/AdvancedQuery/eval/transform.py
Products/AdvancedQuery/eval/tree.py
Products/AdvancedQuery/eval/adapter/__init__.py
Products/AdvancedQuery/eval/adapter/booleanindex.py
Products/AdvancedQuery/eval/adapter/booleanindex.zcml
Products/AdvancedQuery/eval/adapter/cmfcore.py
Products/AdvancedQuery/eval/adapter/cmfcore.zcml
Products/AdvancedQuery/eval/adapter/configure.zcml
Products/AdvancedQuery/eval/adapter/daterangeindex.py
Products/AdvancedQuery/eval/adapter/daterangeindex.zcml
Products/AdvancedQuery/eval/adapter/index.py
Products/AdvancedQuery/eval/adapter/keywordindex.py
Products/AdvancedQuery/eval/adapter/keywordindex.zcml
Products/AdvancedQuery/eval/adapter/unindex.py
Products/AdvancedQuery/eval/adapter/unindex.zcml
Products/AdvancedQuery/eval/adapter/zcatalog.py
Products/AdvancedQuery/eval/adapter/query/__init__.py
Products/AdvancedQuery/eval/adapter/query/configure.zcml
Products/AdvancedQuery/eval/adapter/query/converter/__init__.py
Products/AdvancedQuery/eval/adapter/query/converter/configure.zcml
Products/AdvancedQuery/eval/adapter/query/converter/pathindex.py
Products/AdvancedQuery/eval/adapter/query/converter/tests.py
Products/AdvancedQuery/eval/adapter/query/converter/topicindex.py
Products/AdvancedQuery/eval/adapter/query/converter/zctextindex.py
Products/AdvancedQuery/eval/adapter/query/optimizer/__init__.py
Products/AdvancedQuery/eval/adapter/query/optimizer/configure.zcml
