Metadata-Version: 1.1
Name: Products.AdvancedQuery
Version: 4.1
Summary: Flexible high level search construction and execution for Zope (>= 4)
Home-page: https://pypi.org/project/Products.AdvancedQuery/
Author: Dieter Maurer
Author-email: dieter@handshake.de
License: BSD (see "Products/AdvancedQuery/LICENSE.txt", for details)
Keywords: Zope,flexible,search,construction,execution
Platform: UNKNOWN
Classifier: Development Status :: 5 - Production/Stable
Classifier: Intended Audience :: Developers
Classifier: License :: OSI Approved :: BSD License
Classifier: Framework :: Zope
Classifier: Framework :: Zope :: 4
Classifier: Operating System :: OS Independent
Classifier: Programming Language :: Python
Classifier: Programming Language :: Python :: 2.7
Classifier: Programming Language :: Python :: 3
Classifier: Topic :: Utilities
